cloudfile/__init__.py
cloudfile/__main__.py
cloudfile/add_file.py
cloudfile/ask_confermation.py
cloudfile/check_downloaded.py
cloudfile/cloudfile.py
cloudfile/extract.py
cloudfile/google_drive.py
cloudfile/restore.py
cloudfile/save.py
cloudfile/google/__init__.py
cloudfile/google/google_drive.py
cloudfile-0.2.11.dist-info/LICENSE
cloudfile-0.2.11.dist-info/METADATA
cloudfile-0.2.11.dist-info/WHEEL
cloudfile-0.2.11.dist-info/entry_points.txt
cloudfile-0.2.11.dist-info/top_level.txt
cloudfile-0.2.11.dist-info/RECORD
