Metadata-Version: 2.1
Name: cloudfile
Version: 0.2.11
Summary: Upload and restore large files in the intented location.
Home-page: https://github.com/takotab/cloudfile
Author: Tako Tabak
Author-email: takotabak@gmail.com
License: MIT
Platform: UNKNOWN
Classifier: License :: OSI Approved :: MIT License
Classifier: Programming Language :: Python :: 3
Classifier: Programming Language :: Python :: 3.6
Classifier: Programming Language :: Python :: 3.7
Requires-Dist: wget
Requires-Dist: fire
